insilico_aws/__init__.py
insilico_aws/client.py
insilico_aws/resources.json
insilico_aws/resources.py
insilico_aws/utils.py
insilico_aws/examples/nach01/nach01-Algorithm.ipynb
insilico_aws/examples/nach01/bbbp/request.csv
insilico_aws/examples/nach01/bbbp/test.csv
insilico_aws/examples/nach01/bbbp/train.csv
insilico_aws-1.2.12.dist-info/licenses/LICENSE
insilico_aws-1.2.12.dist-info/METADATA
insilico_aws-1.2.12.dist-info/WHEEL
insilico_aws-1.2.12.dist-info/top_level.txt
insilico_aws-1.2.12.dist-info/RECORD
