Metadata-Version: 2.4
Name: insilico-aws
Version: 1.2.12
Summary: A python package for interacting with Insilico Medicine's products deployed on AWS
Author-email: insilico team <chemistry42@insillicomedicine.com>
Project-URL: homepage, https://pharma.ai/
Project-URL: repository, https://github.com/insilicomedicine/insilico-aws
Project-URL: documentation, https://github.com/insilicomedicine/insilico-aws/blob/main/README.md
Project-URL: Bug Tracker, https://github.com/insilicomedicine/insilico-aws/issues
License-File: LICENSE
Requires-Dist: sagemaker
Provides-Extra: dev
Requires-Dist: mypy==1.15.0; extra == "dev"
Requires-Dist: ruff==0.11.4; extra == "dev"
Requires-Dist: build==1.2.2; extra == "dev"
Requires-Dist: twine==6.1.0; extra == "dev"
Dynamic: license-file
